basic_twitter_nlp/__init__.py
basic_twitter_nlp/basic_twitter_npl.py
basictwitternlp-0.1.1.dist-info/LICENSE.txt
basictwitternlp-0.1.1.dist-info/METADATA
basictwitternlp-0.1.1.dist-info/WHEEL
basictwitternlp-0.1.1.dist-info/top_level.txt
basictwitternlp-0.1.1.dist-info/RECORD
