Metadata-Version: 2.1
Name: basictwitternlp
Version: 0.1.1
Summary: Scrape Twitter based off query and runs NLTK vader and cos similarity model
Home-page: https://github.com/RobertEdwardes/political_twitter/tree/master/Package
Author: Robert Edwardes
Author-email: robie@fairlines.org
License: UNKNOWN
Platform: UNKNOWN
Classifier: Development Status :: 4 - Beta
Classifier: License :: OSI Approved :: MIT License
Classifier: Programming Language :: Python :: 3
Classifier: Programming Language :: Python :: 3.6
Classifier: Programming Language :: Python :: 3.7
Classifier: Programming Language :: Python :: 3.8
Classifier: Programming Language :: Python :: 3.9
Classifier: Programming Language :: Python :: 3.10
Classifier: Programming Language :: Python :: 3 :: Only
Requires-Python: >=3.6, <4
License-File: LICENSE.txt
Requires-Dist: datetime
Requires-Dist: sqlite3
Requires-Dist: request
Requires-Dist: re
Requires-Dist: nltk
Requires-Dist: pandas
Requires-Dist: numpy
Requires-Dist: sklearn
